{
  "version": "7",
  "dialect": "postgresql",
  "entries": [
    {
      "idx": 0,
      "version": "7",
      "when": 1782382385321,
      "tag": "0000_unknown_clint_barton",
      "breakpoints": true
    },
    {
      "idx": 1,
      "version": "7",
      "when": 1782384847617,
      "tag": "0001_mean_magdalene",
      "breakpoints": true
    },
    {
      "idx": 2,
      "version": "7",
      "when": 1782394316861,
      "tag": "0002_normal_toad",
      "breakpoints": true
    },
    {
      "idx": 3,
      "version": "7",
      "when": 1782405143456,
      "tag": "0003_left_strong_guy",
      "breakpoints": true
    },
    {
      "idx": 4,
      "version": "7",
      "when": 1782472720970,
      "tag": "0004_regular_polaris",
      "breakpoints": true
    },
    {
      "idx": 5,
      "version": "7",
      "when": 1782563293964,
      "tag": "0005_sturdy_imperial_guard",
      "breakpoints": true
    },
    {
      "idx": 6,
      "version": "7",
      "when": 1782566024932,
      "tag": "0006_flimsy_micromacro",
      "breakpoints": true
    },
    {
      "idx": 7,
      "version": "7",
      "when": 1782566436442,
      "tag": "0007_dapper_xavin",
      "breakpoints": true
    },
    {
      "idx": 8,
      "version": "7",
      "when": 1782587954017,
      "tag": "0008_unknown_turbo",
      "breakpoints": true
    },
    {
      "idx": 9,
      "version": "7",
      "when": 1782738108162,
      "tag": "0009_lying_namor",
      "breakpoints": true
    },
    {
      "idx": 10,
      "version": "7",
      "when": 1782757034128,
      "tag": "0010_provider_operation_status",
      "breakpoints": true
    },
    {
      "idx": 11,
      "version": "7",
      "when": 1782757904672,
      "tag": "0011_job_run_external_queue_idempotency",
      "breakpoints": true
    },
    {
      "idx": 12,
      "version": "7",
      "when": 1782816884029,
      "tag": "0012_loose_synch",
      "breakpoints": true
    },
    {
      "idx": 13,
      "version": "7",
      "when": 1782841787558,
      "tag": "0013_bored_alice",
      "breakpoints": true
    },
    {
      "idx": 14,
      "version": "7",
      "when": 1782910866210,
      "tag": "0014_rollback_point_idempotency",
      "breakpoints": true
    },
    {
      "idx": 15,
      "version": "7",
      "when": 1782925665471,
      "tag": "0015_volatile_vengeance",
      "breakpoints": true
    },
    {
      "idx": 16,
      "version": "7",
      "when": 1782942599826,
      "tag": "0016_tough_lockjaw",
      "breakpoints": true
    },
    {
      "idx": 17,
      "version": "7",
      "when": 1782987582122,
      "tag": "0017_agent_runs_opportunity_classification",
      "breakpoints": true
    },
    {
      "idx": 18,
      "version": "7",
      "when": 1783094727110,
      "tag": "0018_rare_gateway",
      "breakpoints": true
    },
    {
      "idx": 19,
      "version": "7",
      "when": 1783097455507,
      "tag": "0019_active_agent_run_guard",
      "breakpoints": true
    },
    {
      "idx": 20,
      "version": "7",
      "when": 1783165395656,
      "tag": "0020_misty_blacklash",
      "breakpoints": true
    },
    {
      "idx": 21,
      "version": "7",
      "when": 1783243155371,
      "tag": "0021_steep_wiccan",
      "breakpoints": true
    },
    {
      "idx": 22,
      "version": "7",
      "when": 1783255045286,
      "tag": "0022_useful_violations",
      "breakpoints": true
    },
    {
      "idx": 23,
      "version": "7",
      "when": 1783422386000,
      "tag": "0023_release_verification_active_guard",
      "breakpoints": true
    },
    {
      "idx": 24,
      "version": "7",
      "when": 1783427378171,
      "tag": "0024_gifted_vertigo",
      "breakpoints": true
    },
    {
      "idx": 25,
      "version": "7",
      "when": 1783450146337,
      "tag": "0025_eager_raza",
      "breakpoints": true
    },
    {
      "idx": 26,
      "version": "7",
      "when": 1783451592245,
      "tag": "0026_page_version_immutability",
      "breakpoints": true
    },
    {
      "idx": 27,
      "version": "7",
      "when": 1783452678309,
      "tag": "0027_page_version_freeze_completion",
      "breakpoints": true
    },
    {
      "idx": 28,
      "version": "7",
      "when": 1783454000000,
      "tag": "0028_page_proposal_route_uniqueness",
      "breakpoints": true
    },
    {
      "idx": 29,
      "version": "7",
      "when": 1783456924183,
      "tag": "0029_quiet_deadpool",
      "breakpoints": true
    },
    {
      "idx": 30,
      "version": "7",
      "when": 1783460400000,
      "tag": "0030_page_section_note_approval_blocker_lock",
      "breakpoints": true
    },
    {
      "idx": 31,
      "version": "7",
      "when": 1783501442867,
      "tag": "0031_salty_warpath",
      "breakpoints": true
    },
    {
      "idx": 32,
      "version": "7",
      "when": 1783684705545,
      "tag": "0032_low_boom_boom",
      "breakpoints": true
    },
    {
      "idx": 33,
      "version": "7",
      "when": 1783847724478,
      "tag": "0033_hot_scarecrow",
      "breakpoints": true
    },
    {
      "idx": 34,
      "version": "7",
      "when": 1783880238078,
      "tag": "0034_section_copy_suggestions",
      "breakpoints": true
    },
    {
      "idx": 35,
      "version": "7",
      "when": 1783892227203,
      "tag": "0035_media_assets",
      "breakpoints": true
    }
  ]
}